llama_index/llms/cortex/__init__.py
llama_index/llms/cortex/base.py
llama_index/llms/cortex/utils.py
llama_index_llms_cortex-0.4.1.dist-info/METADATA
llama_index_llms_cortex-0.4.1.dist-info/WHEEL
llama_index_llms_cortex-0.4.1.dist-info/licenses/LICENSE
llama_index_llms_cortex-0.4.1.dist-info/RECORD
