Metadata-Version: 2.4
Name: llama-index-llms-cortex
Version: 0.4.1
Summary: llama-index llms cortex integration
Author-email: Christopher Klapperich <cklapperichmn@gmail.com>, Quinton Mays <qmazedev@gmail.com>
License-Expression: MIT
License-File: LICENSE
Requires-Python: <4.0,>3.9.1
Requires-Dist: aiohttp<4,>=3.11.11
Requires-Dist: cryptography>=44.0.0
Requires-Dist: llama-index-core<0.15,>=0.13.0
Requires-Dist: pyjwt<3,>=2.10.1
